pyloggering/__init__.py
pyloggering/pyloggering.py
pyloggering-1.0.1.dist-info/licenses/LICENSE
pyloggering-1.0.1.dist-info/METADATA
pyloggering-1.0.1.dist-info/WHEEL
pyloggering-1.0.1.dist-info/top_level.txt
pyloggering-1.0.1.dist-info/RECORD
