Metadata-Version: 2.4
Name: pyloggering
Version: 1.0.1
Summary: Module for sumple logging
Home-page: https://github.com/K1AYPVA/logger
Author: K1ayPVA
Author-email: kegor6137@gmail.com
Project-URL: Documentation, https://github.com/K1AYPVA/logger/tree/main
Keywords: logging python
Classifier: License :: OSI Approved :: MIT License
Requires-Python: >=3.10.9
License-File: LICENSE
Requires-Dist: colorama>=0.4.6
Dynamic: author
Dynamic: author-email
Dynamic: classifier
Dynamic: description
Dynamic: description-content-type
Dynamic: home-page
Dynamic: keywords
Dynamic: license-file
Dynamic: project-url
Dynamic: requires-dist
Dynamic: requires-python
Dynamic: summary
